lowrapper/__init__.py
lowrapper/aio.py
lowrapper/client.py
lowrapper-1.0.3.dist-info/LICENSE
lowrapper-1.0.3.dist-info/METADATA
lowrapper-1.0.3.dist-info/WHEEL
lowrapper-1.0.3.dist-info/top_level.txt
lowrapper-1.0.3.dist-info/RECORD
