Metadata-Version: 2.1
Name: lowrapper
Version: 1.0.3
Summary: Make API wrapper in fast, easy.
Home-page: https://github.com/tasuren/lowrapper
Author: tasuren
Author-email: tasuren5@gmail.com
License: MIT
Project-URL: Documentation, https://tasuren.github.io/lowrapper/
Keywords: api wrapper
Platform: UNKNOWN
Classifier: Programming Language :: Python :: 3.8
Classifier: Programming Language :: Python :: 3.9
License-File: LICENSE
Requires-Dist: requests
